<?xml version="1.0" encoding="utf-8"?>
<!-- for the partition: /product -->
<permissions>
    <privapp-permissions package="com.android.contacts">
        <permission name="android.permission.GET_ACCOUNTS_PRIVILEGED"/>
        <permission name="android.permission.READ_PRIVILEGED_PHONE_STATE"/>
        <permission name="android.permission.START_ACTIVITIES_FROM_BACKGROUND"/>
    </privapp-permissions>

    <privapp-permissions package="com.aura.oobe.ntt">
        <permission name="android.permission.INSTALL_PACKAGES"/>
    </privapp-permissions>

    <privapp-permissions package="com.google.android.apps.carrier.carrierwifi">
        <permission name="android.permission.NETWORK_CARRIER_PROVISIONING"/>
        <permission name="android.permission.READ_PRIVILEGED_PHONE_STATE"/>
    </privapp-permissions>

    <privapp-permissions package="com.nttdocomo.android.apnsw">
        <permission name="android.permission.START_ACTIVITIES_FROM_BACKGROUND"/>
        <permission name="android.permission.WRITE_APN_SETTINGS"/>
    </privapp-permissions>

    <privapp-permissions package="com.nttdocomo.android.applicationmanager">
        <permission name="android.permission.INSTALL_PACKAGES"/>
        <permission name="android.permission.PACKAGE_USAGE_STATS"/>
        <permission name="android.permission.READ_PRIVILEGED_PHONE_STATE"/>
        <permission name="android.permission.START_ACTIVITIES_FROM_BACKGROUND"/>
        <permission name="android.permission.WRITE_APN_SETTINGS"/>
    </privapp-permissions>

    <privapp-permissions package="com.nttdocomo.android.devicehelp">
        <permission name="android.permission.PACKAGE_USAGE_STATS"/>
        <permission name="android.permission.READ_PRIVILEGED_PHONE_STATE"/>
        <permission name="android.permission.START_ACTIVITIES_FROM_BACKGROUND"/>
        <permission name="android.permission.STOP_APP_SWITCHES"/>
        <permission name="android.permission.WRITE_SECURE_SETTINGS"/>
    </privapp-permissions>

    <!-- Additional permissions on top of privapp-permissions-platform.xml -->
    <privapp-permissions package="com.nttdocomo.android.networkservice">
        <permission name="android.permission.BIND_INCALL_SERVICE"/>
        <permission name="android.permission.CONTROL_INCALL_EXPERIENCE"/>
        <permission name="android.permission.WRITE_APN_SETTINGS"/>
        <permission name="android.permission.WRITE_SECURE_SETTINGS"/>
    </privapp-permissions>

    <privapp-permissions package="com.nttdocomo.android.sdcardbackup">
        <permission name="android.permission.LOCAL_MAC_ADDRESS"/>
    </privapp-permissions>

    <privapp-permissions package="com.nttdocomo.android.wipe">
        <permission name="android.permission.INTERACT_ACROSS_USERS"/>
        <permission name="android.permission.MANAGE_USERS"/>
        <permission name="android.permission.MODIFY_PHONE_STATE"/>
        <permission name="android.permission.READ_PRIVILEGED_PHONE_STATE"/>
    </privapp-permissions>

    <privapp-permissions package="com.sonyericsson.docomo.settings">
        <permission name="android.permission.MANAGE_USERS"/>
        <permission name="android.permission.WRITE_SECURE_SETTINGS"/>
    </privapp-permissions>

    <privapp-permissions package="com.sonymobile.gameenhancer">
        <permission name="android.permission.BROADCAST_CLOSE_SYSTEM_DIALOGS"/>
        <permission name="android.permission.CAPTURE_AUDIO_OUTPUT"/>
        <permission name="android.permission.GET_ACCOUNTS_PRIVILEGED"/>
        <permission name="android.permission.INTERACT_ACROSS_USERS"/>
        <permission name="android.permission.MANAGE_USERS"/>
        <permission name="android.permission.MODIFY_AUDIO_ROUTING"/>
        <permission name="android.permission.MODIFY_PHONE_STATE"/>
        <permission name="android.permission.PACKAGE_USAGE_STATS"/>
        <permission name="android.permission.READ_PRIVILEGED_PHONE_STATE"/>
        <permission name="android.permission.REAL_GET_TASKS"/>
        <permission name="android.permission.START_ACTIVITIES_FROM_BACKGROUND"/>
        <permission name="android.permission.STATUS_BAR"/>
        <permission name="android.permission.UPDATE_APP_OPS_STATS"/>
        <permission name="android.permission.WRITE_SECURE_SETTINGS"/>
        <permission name="com.sonymobile.gameenhancer.permission.DETECT_KEY_EVENT"/>
        <permission name="com.sonymobile.gameenhancer.permission.INPUT_STATUS"/>
    </privapp-permissions>

    <privapp-permissions package="com.sonymobile.gameenhancer.api">
        <permission name="android.permission.INTERACT_ACROSS_USERS"/>
        <permission name="android.permission.MANAGE_USERS"/>
        <permission name="android.permission.REAL_GET_TASKS"/>
    </privapp-permissions>

    <privapp-permissions package="com.sonymobile.gameenhancer.monitor">
        <permission name="android.permission.MANAGE_USERS"/>
        <permission name="android.permission.REAL_GET_TASKS"/>
        <permission name="android.permission.WRITE_SECURE_SETTINGS"/>
    </privapp-permissions>

    <privapp-permissions package="com.sonymobile.moviecreator">
        <permission name="android.permission.MOUNT_UNMOUNT_FILESYSTEMS"/>
        <permission name="android.permission.WRITE_MEDIA_STORAGE"/>
    </privapp-permissions>

    <privapp-permissions package="com.sonymobile.photopro">
        <permission name="android.permission.WRITE_SECURE_SETTINGS"/>
    </privapp-permissions>

    <privapp-permissions package="com.sonymobile.puk1locksupport">
        <permission name="android.permission.READ_PRIVILEGED_PHONE_STATE"/>
        <permission name="android.permission.START_ACTIVITIES_FROM_BACKGROUND"/>
    </privapp-permissions>

    <privapp-permissions package="com.sonymobile.simplehome">
        <permission name="android.permission.BIND_APPWIDGET"/>
        <permission name="android.permission.CHANGE_CONFIGURATION"/>
        <permission name="android.permission.MANAGE_USERS"/>
        <permission name="android.permission.RECEIVE_STK_COMMANDS"/>
        <permission name="android.permission.WRITE_SECURE_SETTINGS"/>
    </privapp-permissions>

    <privapp-permissions package="com.sonymobile.wirelesschargemanager">
        <permission name="android.permission.INTERACT_ACROSS_USERS"/>
    </privapp-permissions>

    <privapp-permissions package="jp.co.nttdocomo.anshinmode">
        <permission name="android.permission.INTERACT_ACROSS_USERS"/>
        <permission name="android.permission.MANAGE_USERS"/>
        <permission name="android.permission.REAL_GET_TASKS"/>
        <permission name="android.permission.REBOOT"/>
        <permission name="android.permission.START_ACTIVITIES_FROM_BACKGROUND"/>
        <permission name="android.permission.STOP_APP_SWITCHES"/>
    </privapp-permissions>

    <privapp-permissions package="jp.co.nttdocomo.carriermail">
        <permission name="android.permission.READ_PRIVILEGED_PHONE_STATE"/>
        <permission name="android.permission.REAL_GET_TASKS"/>
    </privapp-permissions>

    <privapp-permissions package="jp.co.sony.mc.usbextoutaudio">
        <permission name="android.permission.START_ACTIVITIES_FROM_BACKGROUND"/>
    </privapp-permissions>

</permissions>
